agentgateway/__init__.py
agentgateway/agent_gateway.py
agentgateway/config.yaml
agentgateway/adapters/__init__.py
agentgateway/adapters/anthropic_claude_agent.py
agentgateway/adapters/bedrock_converse_agent.py
agentgateway/adapters/fireworks_ai_agent.py
agentgateway/adapters/groq_agent.py
agentgateway/adapters/openai_gpt_agent.py
agentgateway/adapters/together_ai_agent.py
agentgateway/core/__init__.py
agentgateway/core/abstract_agent.py
agentgateway/core/abstract_tool.py
agentgateway/core/conversation_manager.py
agentgateway/core/dynamo_conversation_manager.py
agentgateway/core/message.py
agentgateway/core/prompt.py
agentgateway/core/redis_conversation_manager.py
agentgateway/core/response.py
agentgateway/tools/__init__.py
agentgateway/tools/askuser_tool.py
agentgateway/tools/calculator_tool.py
agentgateway/tools/sentiment_analysis_tool.py
agentgateway/tools/text_summarization_tool.py
agentgateway/tools/tool_manager.py
agentgateway/tools/topic_detection_tool.py
agentgateway/tools/translate_tool.py
agentgateway/tools/weather_tool.py
agentgateway/tools/web_search_tool.py
agentgateway/utils/__init__.py
agentgateway/utils/agent_logger.py
agentgateway/utils/config_manager.py
agentgateway-1.1.9.dist-info/LICENSE
agentgateway-1.1.9.dist-info/METADATA
agentgateway-1.1.9.dist-info/WHEEL
agentgateway-1.1.9.dist-info/top_level.txt
agentgateway-1.1.9.dist-info/RECORD
