Metadata-Version: 2.1
Name: agentgateway
Version: 1.1.9
Summary: A centralized framework to use a model of your choice for your agentic usecases.
Home-page: https://github.com/santoshameti/agentgateway
Author: Santosh Ameti
Author-email: santosh.ameti@gmail.com
License: MIT
Classifier: Programming Language :: Python :: 3
Classifier: License :: OSI Approved :: MIT License
Classifier: Operating System :: OS Independent
Requires-Python: >=3.6
License-File: LICENSE
Requires-Dist: boto3~=1.35.36
Requires-Dist: python-dotenv~=1.0.1
Requires-Dist: anthropic~=0.34.2
Requires-Dist: openai~=1.51.2
Requires-Dist: geopy~=2.4.1
Requires-Dist: botocore~=1.35.32
Requires-Dist: pytest~=8.3.3
Requires-Dist: groq~=0.11.0
Requires-Dist: bs4~=0.0.2
Requires-Dist: requests~=2.32.3
Requires-Dist: beautifulsoup4~=4.12.3
Requires-Dist: PyYAML~=6.0.2
Requires-Dist: redis~=5.1.1
Requires-Dist: agentgateway~=1.1.0
Requires-Dist: setuptools~=75.4.0
Requires-Dist: textblob~=0.18.0.post0
